geodefi/__init__.py
geodefi/abis/holesky/middleware/ERC20Middleware.json
geodefi/abis/holesky/middleware/ERC20PermitMiddleware.json
geodefi/abis/holesky/middleware/ERC20RebaseMiddleware.json
geodefi/abis/holesky/middleware/ERC20RebasePermitMiddleware.json
geodefi/abis/holesky/package/Portal.json
geodefi/abis/holesky/package/WithdrawalPackage.json
geodefi/abis/holesky/token/gETH.json
geodefi/classes/__init__.py
geodefi/classes/beacon.py
geodefi/classes/id.py
geodefi/classes/operator.py
geodefi/classes/pool.py
geodefi/classes/portal.py
geodefi/classes/token.py
geodefi/classes/validator.py
geodefi/exceptions/__init__.py
geodefi/geodefi.py
geodefi/globals/__init__.py
geodefi/globals/beacon.py
geodefi/globals/constants.py
geodefi/globals/id.py
geodefi/globals/network.py
geodefi/globals/token.py
geodefi/globals/validator.py
geodefi/utils/__init__.py
geodefi/utils/abi.py
geodefi/utils/crypto.py
geodefi/utils/id.py
geodefi/utils/solidity.py
geodefi/utils/token.py
geodefi/utils/version.py
geodefi/utils/wrappers.py
geodefi-3.2.0.dist-info/LICENSE
geodefi-3.2.0.dist-info/METADATA
geodefi-3.2.0.dist-info/WHEEL
geodefi-3.2.0.dist-info/RECORD
