Metadata-Version: 2.1
Name: geodefi
Version: 3.2.0
Summary: Python SDK for Geodefi Ecosystem
Author: 0xIceBear
Requires-Python: >=3.8,<3.13
Classifier: Programming Language :: Python :: 3
Classifier: Programming Language :: Python :: 3.8
Classifier: Programming Language :: Python :: 3.9
Classifier: Programming Language :: Python :: 3.10
Classifier: Programming Language :: Python :: 3.11
Classifier: Programming Language :: Python :: 3.12
Requires-Dist: web3 (>=6.20.0,<7.0.0)
